{
    "CH": {
        "510.0": 1,
        "1980.0": 1,
        "2300.0": 1
    },
    "PK": {
        "396.0": 2
    },
    "TT": {
        "396.0": 1,
        "159.0": 3
    },
    "GR": {
        "396.0": 3,
        "159.0": 2
    },
    "US": {
        "396.0": 3,
        "853.0": 4,
        "159.0": 7
    },
    "CA": {
        "396.0": 2,
        "853.0": 1,
        "159.0": 5,
        "19890.0": 1
    },
    "IN": {
        "396.0": 4,
        "3590.0": 1,
        "159.0": 2,
        "1980.0": 1,
        "19890.0": 4
    },
    "AU": {
        "396.0": 1,
        "159.0": 3,
        "2300.0": 1
    },
    "BD": {
        "396.0": 1,
        "19890.0": 1
    },
    "TN": {
        "396.0": 1,
        "159.0": 1
    },
    "ZA": {
        "396.0": 1,
        "159.0": 1
    },
    "RU": {
        "396.0": 1,
        "3590.0": 1,
        "159.0": 1,
        "19890.0": 116
    },
    "HU": {
        "396.0": 3,
        "853.0": 1,
        "19890.0": 1
    },
    "ZW": {
        "396.0": 1
    },
    "NL": {
        "396.0": 1,
        "853.0": 3,
        "3590.0": 1,
        "159.0": 3
    },
    "MT": {
        "396.0": 1
    },
    "IE": {
        "396.0": 1
    },
    "FR": {
        "853.0": 1,
        "159.0": 1,
        "2300.0": 3
    },
    "SE": {
        "853.0": 1,
        "1980.0": 2
    },
    "ET": {
        "3590.0": 1
    },
    "PH": {
        "3590.0": 1,
        "159.0": 15,
        "1980.0": 4,
        "19890.0": 1
    },
    "ML": {
        "3590.0": 1
    },
    "DE": {
        "3590.0": 1,
        "159.0": 3,
        "1980.0": 1
    },
    "TZ": {
        "3590.0": 1
    },
    "AE": {
        "3590.0": 2,
        "159.0": 2
    },
    "RO": {
        "3590.0": 1,
        "159.0": 2,
        "1980.0": 1,
        "19890.0": 2
    },
    "XK": {
        "3590.0": 1
    },
    "BA": {
        "3590.0": 1,
        "159.0": 2
    },
    "KE": {
        "3590.0": 1,
        "159.0": 1,
        "1980.0": 1
    },
    "MY": {
        "159.0": 3
    },
    "PT": {
        "159.0": 3
    },
    "NZ": {
        "159.0": 2
    },
    "RW": {
        "159.0": 1
    },
    "EG": {
        "159.0": 1
    },
    "UG": {
        "159.0": 1
    },
    "BO": {
        "159.0": 1
    },
    "ES": {
        "159.0": 5
    },
    "BR": {
        "159.0": 1,
        "19890.0": 1
    },
    "TR": {
        "159.0": 2,
        "19890.0": 9
    },
    "GH": {
        "159.0": 2
    },
    "IT": {
        "159.0": 1
    },
    "KR": {
        "159.0": 2,
        "2300.0": 1
    },
    "TW": {
        "159.0": 1
    },
    "CN": {
        "159.0": 3,
        "2300.0": 1
    },
    "DZ": {
        "159.0": 1
    },
    "HR": {
        "159.0": 2
    },
    "SG": {
        "159.0": 2,
        "19890.0": 1
    },
    "JP": {
        "159.0": 1
    },
    "GB": {
        "159.0": 3,
        "19890.0": 2
    },
    "NO": {
        "159.0": 1
    },
    "BJ": {
        "159.0": 3
    },
    "IL": {
        "159.0": 1
    },
    "MK": {
        "159.0": 1
    },
    "NP": {
        "159.0": 1
    },
    "BE": {
        "1980.0": 1
    },
    "TH": {
        "19890.0": 14
    },
    "UZ": {
        "19890.0": 1
    },
    "LV": {
        "19890.0": 1
    },
    "AM": {
        "19890.0": 1
    },
    "UA": {
        "19890.0": 13
    },
    "BY": {
        "19890.0": 1
    },
    "GE": {
        "19890.0": 1
    },
    "AZ": {
        "19890.0": 1
    },
    "KZ": {
        "19890.0": 1
    },
    "PL": {
        "19890.0": 2
    },
    "BG": {
        "19890.0": 2
    },
    "SK": {
        "19890.0": 1
    },
    "KH": {
        "19890.0": 1
    },
    "HK": {
        "2300.0": 2
    },
    "SA": {
        "2300.0": 1
    }
}